sh2_util/__init__.py
sh2_util/http.py
sh2_util-0.8.0.dist-info/METADATA
sh2_util-0.8.0.dist-info/WHEEL
sh2_util-0.8.0.dist-info/top_level.txt
sh2_util-0.8.0.dist-info/RECORD
