Metadata-Version: 2.4
Name: sh2-util
Version: 0.8.0
Summary: sh2 tool
Author-email: shark <sharkshore@163.com>
Requires-Python: >=3.12
Requires-Dist: colorama>=0.4.6
Requires-Dist: requests>=2.32.3
